pySSLVision/VisionComm.py
pySSLVision/__init__.py
pySSLVision/protocols/__init__.py
pySSLVision/protocols/messages_robocup_ssl_detection_pb2.py
pySSLVision/protocols/messages_robocup_ssl_geometry_pb2.py
pySSLVision/protocols/messages_robocup_ssl_wrapper_pb2.py
pySSLVision-2.0.0.dist-info/LICENSE
pySSLVision-2.0.0.dist-info/METADATA
pySSLVision-2.0.0.dist-info/WHEEL
pySSLVision-2.0.0.dist-info/top_level.txt
pySSLVision-2.0.0.dist-info/RECORD
