Metadata-Version: 2.1
Name: pySSLVision
Version: 2.0.0
Summary: Creates a network socket to communicate with the SSL Vision
Author: Project-Neon
Author-email: projectneon@gmail.com
License: GNU
License-File: LICENSE
Requires-Dist: protobuf ==3.20.3
